odoo9_addon_hr_public_holidays-9.0.1.0.0-py2.7-nspkg.pth
odoo9_addon_hr_public_holidays-9.0.1.0.0.dist-info/top_level.txt
odoo9_addon_hr_public_holidays-9.0.1.0.0.dist-info/WHEEL
odoo9_addon_hr_public_holidays-9.0.1.0.0.dist-info/RECORD
odoo9_addon_hr_public_holidays-9.0.1.0.0.dist-info/metadata.json
odoo9_addon_hr_public_holidays-9.0.1.0.0.dist-info/DESCRIPTION.rst
odoo9_addon_hr_public_holidays-9.0.1.0.0.dist-info/METADATA
odoo9_addon_hr_public_holidays-9.0.1.0.0.dist-info/namespace_packages.txt
odoo_addons/hr_public_holidays/__openerp__.py
odoo_addons/hr_public_holidays/__init__.py
odoo_addons/hr_public_holidays/README.rst
odoo_addons/hr_public_holidays/security/ir.model.access.csv
odoo_addons/hr_public_holidays/models/hr_public_holidays.py
odoo_addons/hr_public_holidays/models/hr_public_holidays_line.py
odoo_addons/hr_public_holidays/models/__init__.py
odoo_addons/hr_public_holidays/i18n/it.po
odoo_addons/hr_public_holidays/i18n/es.po
odoo_addons/hr_public_holidays/i18n/ar.po
odoo_addons/hr_public_holidays/i18n/ro.po
odoo_addons/hr_public_holidays/i18n/sl.po
odoo_addons/hr_public_holidays/i18n/de.po
odoo_addons/hr_public_holidays/i18n/fr.po
odoo_addons/hr_public_holidays/i18n/pl.po
odoo_addons/hr_public_holidays/i18n/pt_BR.po
odoo_addons/hr_public_holidays/i18n/fi.po
odoo_addons/hr_public_holidays/views/hr_public_holidays_view.xml
odoo_addons/hr_public_holidays/tests/test_public_holidays.py
odoo_addons/hr_public_holidays/tests/__init__.py
odoo_addons/hr_public_holidays/static/description/icon.svg
odoo_addons/hr_public_holidays/static/description/icon.png
